<?xml version="1.0" encoding="UTF-8"?>
<beans xmlns="http://www.springframework.org/schema/beans"
	xmlns:xsi="http://www.w3.org/2001/XMLSchema-instance" xmlns:context="http://www.springframework.org/schema/context"
	xmlns:mvc="http://www.springframework.org/schema/mvc"
	xsi:schemaLocation="http://www.springframework.org/schema/beans
						http://www.springframework.org/schema/beans/spring-beans.xsd
						http://www.springframework.org/schema/context
				        http://www.springframework.org/schema/context/spring-context.xsd
				        http://www.springframework.org/schema/mvc
				        http://www.springframework.org/schema/mvc/spring-mvc.xsd"
	xmlns:tx="http://www.springframework.org/schema/tx">


	<bean id="dataSource" class="org.apache.commons.dbcp.BasicDataSource">
		<property name="driverClassName" value="com.mysql.jdbc.Driver" />
		<property name="url" value="jdbc:mysql://server:3306/db_schema" />
		<property name="username" value="dbuser " />
		<property name="password" value="dbpassword " />
	</bean>
	<bean id="emf"
		class="org.springframework.orm.jpa.LocalContainerEntityManagerFactoryBean">
		<property name="dataSource" ref="dataSource" />
		<property name="packagesToScan" value="bean" />
		<property name="persistenceUnitName" value="Friend" />
		<property name="jpaVendorAdapter" ref="jpaVendorAdapter" />
	</bean>
	<bean id="jpaVendorAdapter"
		class="org.springframework.orm.jpa.vendor.HibernateJpaVendorAdapter">
		<property name="database" value="MYSQL" />
	</bean>
	<bean id="transactionManager" class="org.springframework.orm.jpa.JpaTransactionManager">
		<property name="entityManagerFactory" ref="emf" />
	</bean>
</beans>